minifilter/__init__.py
minifilter/apps.py
minifilter/filters.py
minifilter/forms.py
minifilter/mixins.py
minifilter/templates/minifilter/includes/pagination.html
minifilter/templates/minifilter/includes/parameters.html
minifilter/templates/minifilter/includes/search.html
minifilter/templatetags/__init__.py
minifilter/templatetags/minifilter_extras.py
django_minifilter-0.0.5.dist-info/LICENSE
django_minifilter-0.0.5.dist-info/METADATA
django_minifilter-0.0.5.dist-info/WHEEL
django_minifilter-0.0.5.dist-info/top_level.txt
django_minifilter-0.0.5.dist-info/RECORD
