Metadata-Version: 2.1
Name: django-minifilter
Version: 0.0.5
Summary: Minimal filter and search functionality for django list views.
Author-email: dennisvang <djvg@protonmail.com>
License: BSD 3-Clause License
Project-URL: source, https://github.com/dennisvang/django-minifilter
Project-URL: documentation, https://github.com/dennisvang/django-minifilter
Project-URL: issues, https://github.com/dennisvang/django-minifilter/issues
Classifier: Programming Language :: Python :: 3
Classifier: Framework :: Django
Classifier: License :: OSI Approved :: MIT License
Classifier: Operating System :: OS Independent
Requires-Python: >=3.9
License-File: LICENSE
Requires-Dist: django >=3.2
